telnetio/__init__.py
telnetio/_anyio.py
telnetio/_machine.py
telnetio/_opt.py
telnetio/py.typed
telnetio-0.3.0.dist-info/LICENSE
telnetio-0.3.0.dist-info/WHEEL
telnetio-0.3.0.dist-info/METADATA
telnetio-0.3.0.dist-info/RECORD
