Metadata-Version: 2.1
Name: telnetio
Version: 0.3.0
Summary: Sans-IO telnet parser
Home-page: https://github.com/uSpike/telnetio
License: MIT
Author: Jordan Speicher
Author-email: jordan@jspeicher.com
Requires-Python: >=3.6.2,<4.0.0
Classifier: License :: OSI Approved :: MIT License
Classifier: Programming Language :: Python :: 3
Classifier: Programming Language :: Python :: 3.7
Classifier: Programming Language :: Python :: 3.8
Classifier: Programming Language :: Python :: 3.9
Provides-Extra: anyio
Requires-Dist: anyio (>=3.2.0,<4.0.0); extra == "anyio"
Requires-Dist: async_generator (>=1.10,<2.0); (python_version == "3.6") and (extra == "anyio")
Requires-Dist: dataclasses (>=0.8,<0.9); python_version == "3.6"
